payment_optimizer/__init__.py
payment_optimizer-0.1.dist-info/LICENSE
payment_optimizer-0.1.dist-info/METADATA
payment_optimizer-0.1.dist-info/WHEEL
payment_optimizer-0.1.dist-info/top_level.txt
payment_optimizer-0.1.dist-info/RECORD
