Metadata-Version: 2.1
Name: payment-optimizer
Version: 0.1
Summary: Optimizing the payment process of e-commerce
Author: Elen Sukiasyan, Nane Mambreyan, Areg Amirjanyan, Gayane Ohanjanyan, Hasmik Sahakyan
License: The Unlicense
Classifier: Development Status :: 3 - Alpha
Requires-Python: >=3.10, <3.12
License-File: LICENSE
Requires-Dist: requests
Requires-Dist: pandas >=2.0
